{
  "customers": {
    "TG-0001": {
      "Customer ID": "TG-0001",
      "Name": "Paula López",
      "Email": "paula.lopez1@mailinator.com",
      "Product Purchased": "Wireless Earbuds Air",
      "Purchase Date": "2024-01-26",
      "Amount Spent ($)": 627.32,
      "Age": 33,
      "City": "Medellín",
      "Payment Method": "Credit Card",
      "Last Login Date": "2026-02-23",
      "Membership Status": "Silver"
    },
    "TG-0002": {
      "Customer ID": "TG-0002",
      "Name": "Santiago García",
      "Email": "santiago.garcia2@mailinator.com",
      "Product Purchased": "Laptop Pro X1",
      "Purchase Date": "2024-04-05",
      "Amount Spent ($)": 1273.27,
      "Age": 30,
      "City": "Santiago",
      "Payment Method": "Debit Card",
      "Last Login Date": "2024-11-14",
      "Membership Status": "Gold"
    },
    "TG-0003": {
      "Customer ID": "TG-0003",
      "Name": "Victoria Vargas",
      "Email": "victoria.vargas3@mailinator.com",
      "Product Purchased": "Laptop Pro X1",
      "Purchase Date": "2025-03-05",
      "Amount Spent ($)": 1481.37,
      "Age": 44,
      "City": "Cali",
      "Payment Method": "Bank Transfer",
      "Last Login Date": "2025-06-25",
      "Membership Status": "Bronze"
    },
    "TG-0004": {
      "Customer ID": "TG-0004",
      "Name": "Isabella González",
      "Email": "isabella.gonzalez4@mailinator.com",
      "Product Purchased": "Smartphone Ultra 5G",
      "Purchase Date": "2026-02-20",
      "Amount Spent ($)": 250.0,
      "Age": 22,
      "City": "Ciudad de México",
      "Payment Method": "PayPal",
      "Last Login Date": "2026-05-17",
      "Membership Status": "Silver"
    },
    "TG-0005": {
      "Customer ID": "TG-0005",
      "Name": "David Rodríguez",
      "Email": "david.rodriguez5@mailinator.com",
      "Product Purchased": "Mechanical Keyboard RGB",
      "Purchase Date": "2026-01-17",
      "Amount Spent ($)": 329.56,
      "Age": 50,
      "City": "Medellín",
      "Payment Method": "PayPal",
      "Last Login Date": "2026-05-14",
      "Membership Status": "Gold"
    },
    "TG-0006": {
      "Customer ID": "TG-0006",
      "Name": "Samuel Rivera",
      "Email": "samuel.rivera6@mailinator.com",
      "Product Purchased": "VR Headset Vision",
      "Purchase Date": "2025-08-14",
      "Amount Spent ($)": 192.49,
      "Age": 61,
      "City": "Cúcuta",
      "Payment Method": "PayPal",
      "Last Login Date": "2025-11-20",
      "Membership Status": "Platinum"
    },
    "TG-0007": {
      "Customer ID": "TG-0007",
      "Name": "Joaquín Sánchez",
      "Email": "joaquin.sanchez7@mailinator.com",
      "Product Purchased": "VR Headset Vision",
      "Purchase Date": "2026-06-06",
      "Amount Spent ($)": 709.36,
      "Age": 40,
      "City": "Ciudad de México",
      "Payment Method": "Debit Card",
      "Last Login Date": "2026-06-12",
      "Membership Status": "Bronze"
    },
    "TG-0008": {
      "Customer ID": "TG-0008",
      "Name": "Sofía Ramírez",
      "Email": "sofia.ramirez8@mailinator.com",
      "Product Purchased": "VR Headset Vision",
      "Purchase Date": "2025-12-19",
      "Amount Spent ($)": 197.07,
      "Age": 57,
      "City": "Cali",
      "Payment Method": "Debit Card",
      "Last Login Date": "2026-06-11",
      "Membership Status": "Bronze"
    },
    "TG-0009": {
      "Customer ID": "TG-0009",
      "Name": "Luciana Ramírez",
      "Email": "luciana.ramirez9@mailinator.com",
      "Product Purchased": "Laptop Pro X1",
      "Purchase Date": "2025-10-17",
      "Amount Spent ($)": 824.21,
      "Age": 59,
      "City": "Cúcuta",
      "Payment Method": "Credit Card",
      "Last Login Date": "2026-02-06",
      "Membership Status": "Gold"
    },
    "TG-0010": {
      "Customer ID": "TG-0010",
      "Name": "Luciana Ramírez",
      "Email": "luciana.ramirez10@mailinator.com",
      "Product Purchased": "Monitor 4K UltraView",
      "Purchase Date": "2024-03-08",
      "Amount Spent ($)": 2193.38,
      "Age": 52,
      "City": "Cúcuta",
      "Payment Method": "Bank Transfer",
      "Last Login Date": "2024-10-10",
      "Membership Status": "Bronze"
    },
    "TG-0011": {
      "Customer ID": "TG-0011",
      "Name": "Felipe Castro",
      "Email": "felipe.castro11@mailinator.com",
      "Product Purchased": "Tablet Air 11",
      "Purchase Date": "2024-05-26",
      "Amount Spent ($)": 631.63,
      "Age": 24,
      "City": "Santiago",
      "Payment Method": "PayPal",
      "Last Login Date": "2025-02-21",
      "Membership Status": "Gold"
    },
    "TG-0012": {
      "Customer ID": "TG-0012",
      "Name": "Diego Suárez",
      "Email": "diego.suarez12@mailinator.com",
      "Product Purchased": "Wireless Earbuds Air",
      "Purchase Date": "2025-02-12",
      "Amount Spent ($)": 2493.36,
      "Age": 30,
      "City": "Santiago",
      "Payment Method": "Bank Transfer",
      "Last Login Date": "2026-02-17",
      "Membership Status": "Bronze"
    },
    "TG-0013": {
      "Customer ID": "TG-0013",
      "Name": "Santiago López",
      "Email": "santiago.lopez13@mailinator.com",
      "Product Purchased": "Mechanical Keyboard RGB",
      "Purchase Date": "2024-06-05",
      "Amount Spent ($)": 1984.35,
      "Age": 26,
      "City": "Quito",
      "Payment Method": "Credit Card",
      "Last Login Date": "2026-03-09",
      "Membership Status": "Bronze"
    },
    "TG-0014": {
      "Customer ID": "TG-0014",
      "Name": "Samuel Castro",
      "Email": "samuel.castro14@mailinator.com",
      "Product Purchased": "Laptop Pro X1",
      "Purchase Date": "2025-06-25",
      "Amount Spent ($)": 2154.72,
      "Age": 51,
      "City": "Medellín",
      "Payment Method": "PayPal",
      "Last Login Date": "2025-10-31",
      "Membership Status": "Gold"
    },
    "TG-0015": {
      "Customer ID": "TG-0015",
      "Name": "Daniela López",
      "Email": "daniela.lopez15@mailinator.com",
      "Product Purchased": "Power Bank Max 20K",
      "Purchase Date": "2024-10-27",
      "Amount Spent ($)": 1145.22,
      "Age": 26,
      "City": "Barranquilla",
      "Payment Method": "Debit Card",
      "Last Login Date": "2026-01-15",
      "Membership Status": "Silver"
    },
    "TG-0016": {
      "Customer ID": "TG-0016",
      "Name": "Mateo Torres",
      "Email": "mateo.torres16@mailinator.com",
      "Product Purchased": "Monitor 4K UltraView",
      "Purchase Date": "2026-05-11",
      "Amount Spent ($)": 513.29,
      "Age": 54,
      "City": "Cali",
      "Payment Method": "Credit Card",
      "Last Login Date": "2026-07-14",
      "Membership Status": "Silver"
    },
    "TG-0017": {
      "Customer ID": "TG-0017",
      "Name": "Alejandro García",
      "Email": "alejandro.garcia17@mailinator.com",
      "Product Purchased": "Gaming Console Nova",
      "Purchase Date": "2024-04-24",
      "Amount Spent ($)": 2463.59,
      "Age": 72,
      "City": "Cúcuta",
      "Payment Method": "Credit Card",
      "Last Login Date": "2025-04-30",
      "Membership Status": "Bronze"
    },
    "TG-0018": {
      "Customer ID": "TG-0018",
      "Name": "Antonia Martínez",
      "Email": "antonia.martinez18@mailinator.com",
      "Product Purchased": "Tablet Air 11",
      "Purchase Date": "2024-03-28",
      "Amount Spent ($)": 2043.73,
      "Age": 47,
      "City": "Cali",
      "Payment Method": "Debit Card",
      "Last Login Date": "2026-04-16",
      "Membership Status": "Silver"
    },
    "TG-0019": {
      "Customer ID": "TG-0019",
      "Name": "Emiliano Pérez",
      "Email": "emiliano.perez19@mailinator.com",
      "Product Purchased": "Smart Watch Fit",
      "Purchase Date": "2024-09-28",
      "Amount Spent ($)": 1524.34,
      "Age": 71,
      "City": "Santiago",
      "Payment Method": "Debit Card",
      "Last Login Date": "2026-03-22",
      "Membership Status": "Gold"
    },
    "TG-0020": {
      "Customer ID": "TG-0020",
      "Name": "Luciana Rivera",
      "Email": "luciana.rivera20@mailinator.com",
      "Product Purchased": "Smart Watch Fit",
      "Purchase Date": "2025-03-24",
      "Amount Spent ($)": 1139.68,
      "Age": 49,
      "City": "Cúcuta",
      "Payment Method": "Credit Card",
      "Last Login Date": "2026-06-27",
      "Membership Status": "Bronze"
    },
    "TG-0021": {
      "Customer ID": "TG-0021",
      "Name": "Antonia Vargas",
      "Email": "antonia.vargas21@mailinator.com",
      "Product Purchased": "Power Bank Max 20K",
      "Purchase Date": "2024-08-23",
      "Amount Spent ($)": 37.82,
      "Age": 30,
      "City": "Bogotá",
      "Payment Method": "Debit Card",
      "Last Login Date": "2026-04-17",
      "Membership Status": "Bronze"
    },
    "TG-0022": {
      "Customer ID": "TG-0022",
      "Name": "Santiago Flores",
      "Email": "santiago.flores22@mailinator.com",
      "Product Purchased": "Bluetooth Speaker Boom",
      "Purchase Date": "2024-03-13",
      "Amount Spent ($)": 710.61,
      "Age": 31,
      "City": "Cúcuta",
      "Payment Method": "Debit Card",
      "Last Login Date": "2025-08-21",
      "Membership Status": "Gold"
    },
    "TG-0023": {
      "Customer ID": "TG-0023",
      "Name": "Ximena Suárez",
      "Email": "ximena.suarez23@mailinator.com",
      "Product Purchased": "Mechanical Keyboard RGB",
      "Purchase Date": "2025-08-13",
      "Amount Spent ($)": 1965.85,
      "Age": 31,
      "City": "Cúcuta",
      "Payment Method": "Credit Card",
      "Last Login Date": "2026-04-12",
      "Membership Status": "Bronze"
    },
    "TG-0024": {
      "Customer ID": "TG-0024",
      "Name": "Diego Rivera",
      "Email": "diego.rivera24@mailinator.com",
      "Product Purchased": "Laptop Pro X1",
      "Purchase Date": "2025-03-09",
      "Amount Spent ($)": 2162.31,
      "Age": 45,
      "City": "Medellín",
      "Payment Method": "Credit Card",
      "Last Login Date": "2025-10-05",
      "Membership Status": "Silver"
    },
    "TG-0025": {
      "Customer ID": "TG-0025",
      "Name": "Daniela López",
      "Email": "daniela.lopez25@mailinator.com",
      "Product Purchased": "Wireless Earbuds Air",
      "Purchase Date": "2024-09-11",
      "Amount Spent ($)": 1349.98,
      "Age": 28,
      "City": "Buenos Aires",
      "Payment Method": "Debit Card",
      "Last Login Date": "2025-03-26",
      "Membership Status": "Bronze"
    },
    "TG-0026": {
      "Customer ID": "TG-0026",
      "Name": "Nicolás Martínez",
      "Email": "nicolas.martinez26@mailinator.com",
      "Product Purchased": "Smartphone Ultra 5G",
      "Purchase Date": "2025-03-29",
      "Amount Spent ($)": 2142.79,
      "Age": 71,
      "City": "Bogotá",
      "Payment Method": "Credit Card",
      "Last Login Date": "2026-05-16",
      "Membership Status": "Platinum"
    },
    "TG-0027": {
      "Customer ID": "TG-0027",
      "Name": "Felipe Sánchez",
      "Email": "felipe.sanchez27@mailinator.com",
      "Product Purchased": "Mechanical Keyboard RGB",
      "Purchase Date": "2024-06-19",
      "Amount Spent ($)": 1213.76,
      "Age": 47,
      "City": "Bogotá",
      "Payment Method": "Debit Card",
      "Last Login Date": "2025-08-09",
      "Membership Status": "Bronze"
    },
    "TG-0028": {
      "Customer ID": "TG-0028",
      "Name": "Luciana Ramírez",
      "Email": "luciana.ramirez28@mailinator.com",
      "Product Purchased": "Power Bank Max 20K",
      "Purchase Date": "2026-03-13",
      "Amount Spent ($)": 727.41,
      "Age": 45,
      "City": "Santiago",
      "Payment Method": "Bank Transfer",
      "Last Login Date": "2026-06-21",
      "Membership Status": "Bronze"
    },
    "TG-0029": {
      "Customer ID": "TG-0029",
      "Name": "Andrés González",
      "Email": "andres.gonzalez29@mailinator.com",
      "Product Purchased": "Power Bank Max 20K",
      "Purchase Date": "2024-02-29",
      "Amount Spent ($)": 1364.63,
      "Age": 63,
      "City": "Ciudad de México",
      "Payment Method": "Credit Card",
      "Last Login Date": "2025-10-14",
      "Membership Status": "Bronze"
    },
    "TG-0030": {
      "Customer ID": "TG-0030",
      "Name": "Alejandro Ortiz",
      "Email": "alejandro.ortiz30@mailinator.com",
      "Product Purchased": "Tablet Air 11",
      "Purchase Date": "2026-05-23",
      "Amount Spent ($)": 161.05,
      "Age": 26,
      "City": "Medellín",
      "Payment Method": "Debit Card",
      "Last Login Date": "2026-06-25",
      "Membership Status": "Bronze"
    },
    "TG-0031": {
      "Customer ID": "TG-0031",
      "Name": "Valentina Sánchez",
      "Email": "valentina.sanchez31@mailinator.com",
      "Product Purchased": "Drone Explorer Mini",
      "Purchase Date": "2025-02-17",
      "Amount Spent ($)": 1432.79,
      "Age": 72,
      "City": "Quito",
      "Payment Method": "Credit Card",
      "Last Login Date": "2025-06-19",
      "Membership Status": "Silver"
    },
    "TG-0032": {
      "Customer ID": "TG-0032",
      "Name": "Diego Suárez",
      "Email": "diego.suarez32@mailinator.com",
      "Product Purchased": "Smart Watch Fit",
      "Purchase Date": "2025-08-01",
      "Amount Spent ($)": 2338.06,
      "Age": 36,
      "City": "Ciudad de México",
      "Payment Method": "Debit Card",
      "Last Login Date": "2026-04-25",
      "Membership Status": "Bronze"
    },
    "TG-0033": {
      "Customer ID": "TG-0033",
      "Name": "Isabella Torres",
      "Email": "isabella.torres33@mailinator.com",
      "Product Purchased": "Laptop Pro X1",
      "Purchase Date": "2025-04-13",
      "Amount Spent ($)": 2340.61,
      "Age": 64,
      "City": "Lima",
      "Payment Method": "Credit Card",
      "Last Login Date": "2025-09-21",
      "Membership Status": "Bronze"
    },
    "TG-0034": {
      "Customer ID": "TG-0034",
      "Name": "Sofía Ortiz",
      "Email": "sofia.ortiz34@mailinator.com",
      "Product Purchased": "Smart Watch Fit",
      "Purchase Date": "2024-09-28",
      "Amount Spent ($)": 2204.53,
      "Age": 38,
      "City": "Ciudad de México",
      "Payment Method": "PayPal",
      "Last Login Date": "2025-02-10",
      "Membership Status": "Bronze"
    },
    "TG-0035": {
      "Customer ID": "TG-0035",
      "Name": "Regina Vargas",
      "Email": "regina.vargas35@mailinator.com",
      "Product Purchased": "VR Headset Vision",
      "Purchase Date": "2025-12-21",
      "Amount Spent ($)": 2459.95,
      "Age": 55,
      "City": "Santiago",
      "Payment Method": "Credit Card",
      "Last Login Date": "2026-03-08",
      "Membership Status": "Silver"
    },
    "TG-0036": {
      "Customer ID": "TG-0036",
      "Name": "Emiliano Torres",
      "Email": "emiliano.torres36@mailinator.com",
      "Product Purchased": "Smartphone Ultra 5G",
      "Purchase Date": "2025-11-10",
      "Amount Spent ($)": 353.03,
      "Age": 72,
      "City": "Medellín",
      "Payment Method": "Debit Card",
      "Last Login Date": "2025-12-06",
      "Membership Status": "Bronze"
    },
    "TG-0037": {
      "Customer ID": "TG-0037",
      "Name": "Samuel González",
      "Email": "samuel.gonzalez37@mailinator.com",
      "Product Purchased": "Gaming Console Nova",
      "Purchase Date": "2026-01-04",
      "Amount Spent ($)": 1724.98,
      "Age": 29,
      "City": "Santiago",
      "Payment Method": "Bank Transfer",
      "Last Login Date": "2026-04-01",
      "Membership Status": "Bronze"
    },
    "TG-0038": {
      "Customer ID": "TG-0038",
      "Name": "Felipe Rodríguez",
      "Email": "felipe.rodriguez38@mailinator.com",
      "Product Purchased": "Laptop Pro X1",
      "Purchase Date": "2024-04-04",
      "Amount Spent ($)": 2076.77,
      "Age": 43,
      "City": "Bogotá",
      "Payment Method": "PayPal",
      "Last Login Date": "2026-01-13",
      "Membership Status": "Gold"
    },
    "TG-0039": {
      "Customer ID": "TG-0039",
      "Name": "Paula Ramírez",
      "Email": "paula.ramirez39@mailinator.com",
      "Product Purchased": "Mechanical Keyboard RGB",
      "Purchase Date": "2024-06-14",
      "Amount Spent ($)": 1388.16,
      "Age": 44,
      "City": "Santiago",
      "Payment Method": "Credit Card",
      "Last Login Date": "2026-07-13",
      "Membership Status": "Bronze"
    },
    "TG-0040": {
      "Customer ID": "TG-0040",
      "Name": "Ximena Hernández",
      "Email": "ximena.hernandez40@mailinator.com",
      "Product Purchased": "Tablet Air 11",
      "Purchase Date": "2025-07-12",
      "Amount Spent ($)": 935.65,
      "Age": 69,
      "City": "Cali",
      "Payment Method": "Bank Transfer",
      "Last Login Date": "2025-07-30",
      "Membership Status": "Bronze"
    }
  }
}